pymongodantic/__init__.py
pymongodantic/collection.py
pymongodantic/example.py
pymongodantic-0.1.0.dist-info/entry_points.txt
pymongodantic-0.1.0.dist-info/LICENSE
pymongodantic-0.1.0.dist-info/WHEEL
pymongodantic-0.1.0.dist-info/METADATA
pymongodantic-0.1.0.dist-info/RECORD
