Metadata-Version: 2.1
Name: pymongodantic
Version: 0.1.0
Summary: `pymongodantic` is a MongoDB ORM working with pydantic thus being directly compatible with tools like FastAPI
Home-page: https://github.com/blitzjb/pymongodantic
License: MIT
Author: BlitzJB.dev
Author-email: blitz04.dev@gmail.com
Requires-Python: >=3.7,<4.0
Classifier: Development Status :: 3 - Alpha
Classifier: Intended Audience :: Developers
Classifier: License :: OSI Approved :: MIT License
Classifier: Operating System :: OS Independent
Classifier: Programming Language :: Python :: 3
Classifier: Programming Language :: Python :: 3.10
Classifier: Programming Language :: Python :: 3.7
Classifier: Programming Language :: Python :: 3.8
Classifier: Programming Language :: Python :: 3.9
Classifier: Topic :: Software Development :: Libraries :: Python Modules
Requires-Dist: dnspython (>=2.2.1,<3.0.0)
Requires-Dist: importlib_metadata (>=4.5.0,<5.0.0); python_version < "3.8"
Requires-Dist: pydantic (>=1.9.1,<2.0.0)
Requires-Dist: pymongo (>=4.1.1,<5.0.0)
Requires-Dist: rich (>=10.14.0,<11.0.0)
Requires-Dist: typer[all] (>=0.4.0,<0.5.0)
Project-URL: Repository, https://github.com/blitzjb/pymongodantic
